[
  {
    "ContainingType": "APIRES.Controllers.ModulosController",
    "Method": "Editar",
    "RelativePath": "api/Modulos/Editar",
    "HttpMethod": "PUT",
    "IsController": true,
    "Order": 0,
    "Parameters": [
      {
        "Name": "objeto",
        "Type": "APIRES.Models.Modulo",
        "IsRequired": true
      }
    ],
    "ReturnTypes": []
  },
  {
    "ContainingType": "APIRES.Controllers.ModulosController",
    "Method": "Eliminar",
    "RelativePath": "api/Modulos/Eliminar/{IdModulo}",
    "HttpMethod": "DELETE",
    "IsController": true,
    "Order": 0,
    "Parameters": [
      {
        "Name": "IdModulo",
        "Type": "System.Int32",
        "IsRequired": true
      }
    ],
    "ReturnTypes": []
  },
  {
    "ContainingType": "APIRES.Controllers.ModulosController",
    "Method": "Guardar",
    "RelativePath": "api/Modulos/Guardar",
    "HttpMethod": "POST",
    "IsController": true,
    "Order": 0,
    "Parameters": [
      {
        "Name": "objeto",
        "Type": "APIRES.Models.Modulo",
        "IsRequired": true
      }
    ],
    "ReturnTypes": []
  },
  {
    "ContainingType": "APIRES.Controllers.ModulosController",
    "Method": "ListaModulo",
    "RelativePath": "api/Modulos/ListaModulo",
    "HttpMethod": "GET",
    "IsController": true,
    "Order": 0,
    "Parameters": [],
    "ReturnTypes": []
  },
  {
    "ContainingType": "APIRES.Controllers.ModulosController",
    "Method": "Obtener",
    "RelativePath": "api/Modulos/Obtener/{IdModulo}",
    "HttpMethod": "GET",
    "IsController": true,
    "Order": 0,
    "Parameters": [
      {
        "Name": "IdModulo",
        "Type": "System.Int32",
        "IsRequired": true
      }
    ],
    "ReturnTypes": []
  },
  {
    "ContainingType": "APIRES.Controllers.RelacionesController",
    "Method": "EditarRelaciones",
    "RelativePath": "api/Relaciones/EditarRelaciones",
    "HttpMethod": "PUT",
    "IsController": true,
    "Order": 0,
    "Parameters": [
      {
        "Name": "IdRol",
        "Type": "System.Int32",
        "IsRequired": false
      },
      {
        "Name": "IdModulo",
        "Type": "System.Int32",
        "IsRequired": false
      }
    ],
    "ReturnTypes": []
  },
  {
    "ContainingType": "APIRES.Controllers.RelacionesController",
    "Method": "Eliminar",
    "RelativePath": "api/Relaciones/Eliminar/{IdRelacione}",
    "HttpMethod": "DELETE",
    "IsController": true,
    "Order": 0,
    "Parameters": [
      {
        "Name": "IdRelacione",
        "Type": "System.Int32",
        "IsRequired": true
      }
    ],
    "ReturnTypes": []
  },
  {
    "ContainingType": "APIRES.Controllers.RelacionesController",
    "Method": "GuardarRelaciones",
    "RelativePath": "api/Relaciones/GuardarRelaciones",
    "HttpMethod": "POST",
    "IsController": true,
    "Order": 0,
    "Parameters": [
      {
        "Name": "IdModolo",
        "Type": "System.Int32",
        "IsRequired": false
      },
      {
        "Name": "idRol",
        "Type": "System.Int32",
        "IsRequired": false
      }
    ],
    "ReturnTypes": []
  },
  {
    "ContainingType": "APIRES.Controllers.RelacionesController",
    "Method": "ListaRelacione",
    "RelativePath": "api/Relaciones/ListaRelacione",
    "HttpMethod": "GET",
    "IsController": true,
    "Order": 0,
    "Parameters": [],
    "ReturnTypes": []
  },
  {
    "ContainingType": "APIRES.Controllers.RelacionesController",
    "Method": "Obtener",
    "RelativePath": "api/Relaciones/Obtener/{IdRelacione}",
    "HttpMethod": "GET",
    "IsController": true,
    "Order": 0,
    "Parameters": [
      {
        "Name": "IdRelacione",
        "Type": "System.Int32",
        "IsRequired": true
      }
    ],
    "ReturnTypes": []
  },
  {
    "ContainingType": "APIRES.Controllers.RolesController",
    "Method": "Editar",
    "RelativePath": "api/Roles/Editar",
    "HttpMethod": "PUT",
    "IsController": true,
    "Order": 0,
    "Parameters": [
      {
        "Name": "objeto",
        "Type": "APIRES.Models.Rol",
        "IsRequired": true
      }
    ],
    "ReturnTypes": []
  },
  {
    "ContainingType": "APIRES.Controllers.RolesController",
    "Method": "Eliminar",
    "RelativePath": "api/Roles/Eliminar/{IdRol}",
    "HttpMethod": "DELETE",
    "IsController": true,
    "Order": 0,
    "Parameters": [
      {
        "Name": "IdRol",
        "Type": "System.Int32",
        "IsRequired": true
      }
    ],
    "ReturnTypes": []
  },
  {
    "ContainingType": "APIRES.Controllers.RolesController",
    "Method": "Guardar",
    "RelativePath": "api/Roles/Guardar",
    "HttpMethod": "POST",
    "IsController": true,
    "Order": 0,
    "Parameters": [
      {
        "Name": "objeto",
        "Type": "APIRES.Models.Rol",
        "IsRequired": true
      }
    ],
    "ReturnTypes": []
  },
  {
    "ContainingType": "APIRES.Controllers.RolesController",
    "Method": "Lista",
    "RelativePath": "api/Roles/Lista",
    "HttpMethod": "GET",
    "IsController": true,
    "Order": 0,
    "Parameters": [],
    "ReturnTypes": []
  },
  {
    "ContainingType": "APIRES.Controllers.RolesController",
    "Method": "Obtener",
    "RelativePath": "api/Roles/Obtener/{IdRol}",
    "HttpMethod": "GET",
    "IsController": true,
    "Order": 0,
    "Parameters": [
      {
        "Name": "IdRol",
        "Type": "System.Int32",
        "IsRequired": true
      }
    ],
    "ReturnTypes": []
  },
  {
    "ContainingType": "APIRES.Controllers.UsuariosController",
    "Method": "EditarUsuario",
    "RelativePath": "api/Usuarios/EditarUsuario",
    "HttpMethod": "PUT",
    "IsController": true,
    "Order": 0,
    "Parameters": [
      {
        "Name": "IdUsuario",
        "Type": "System.Int32",
        "IsRequired": false
      },
      {
        "Name": "nombre",
        "Type": "System.String",
        "IsRequired": false
      },
      {
        "Name": "apellido",
        "Type": "System.String",
        "IsRequired": false
      },
      {
        "Name": "correo",
        "Type": "System.String",
        "IsRequired": false
      },
      {
        "Name": "contrasena",
        "Type": "System.String",
        "IsRequired": false
      },
      {
        "Name": "cargo",
        "Type": "System.String",
        "IsRequired": false
      },
      {
        "Name": "telefono",
        "Type": "System.String",
        "IsRequired": false
      },
      {
        "Name": "idRol",
        "Type": "System.Int32",
        "IsRequired": false
      }
    ],
    "ReturnTypes": []
  },
  {
    "ContainingType": "APIRES.Controllers.UsuariosController",
    "Method": "Eliminar",
    "RelativePath": "api/Usuarios/Eliminar/{IdUsuario}",
    "HttpMethod": "DELETE",
    "IsController": true,
    "Order": 0,
    "Parameters": [
      {
        "Name": "IdUsuario",
        "Type": "System.Int32",
        "IsRequired": true
      }
    ],
    "ReturnTypes": []
  },
  {
    "ContainingType": "APIRES.Controllers.UsuariosController",
    "Method": "GuardarUsuario",
    "RelativePath": "api/Usuarios/GuardarUsuario",
    "HttpMethod": "POST",
    "IsController": true,
    "Order": 0,
    "Parameters": [
      {
        "Name": "nombre",
        "Type": "System.String",
        "IsRequired": false
      },
      {
        "Name": "apellido",
        "Type": "System.String",
        "IsRequired": false
      },
      {
        "Name": "correo",
        "Type": "System.String",
        "IsRequired": false
      },
      {
        "Name": "contrasena",
        "Type": "System.String",
        "IsRequired": false
      },
      {
        "Name": "cargo",
        "Type": "System.String",
        "IsRequired": false
      },
      {
        "Name": "telefono",
        "Type": "System.String",
        "IsRequired": false
      },
      {
        "Name": "idRol",
        "Type": "System.Int32",
        "IsRequired": false
      }
    ],
    "ReturnTypes": []
  },
  {
    "ContainingType": "APIRES.Controllers.UsuariosController",
    "Method": "ListaUsuario",
    "RelativePath": "api/Usuarios/ListaUsuario",
    "HttpMethod": "GET",
    "IsController": true,
    "Order": 0,
    "Parameters": [],
    "ReturnTypes": []
  },
  {
    "ContainingType": "APIRES.Controllers.UsuariosController",
    "Method": "Obtener",
    "RelativePath": "api/Usuarios/Obtener/{IdUsuario}",
    "HttpMethod": "GET",
    "IsController": true,
    "Order": 0,
    "Parameters": [
      {
        "Name": "IdUsuario",
        "Type": "System.Int32",
        "IsRequired": true
      }
    ],
    "ReturnTypes": []
  },
  {
    "ContainingType": "APIRES.Controllers.WeatherForecastController",
    "Method": "Get",
    "RelativePath": "WeatherForecast",
    "HttpMethod": "GET",
    "IsController": true,
    "Order": 0,
    "Parameters": [],
    "ReturnTypes": [
      {
        "Type": "System.Collections.Generic.IEnumerable\u00601[[APIRES.WeatherForecast, APIRES, Version=1.0.0.0, Culture=neutral, PublicKeyToken=null]]",
        "MediaTypes": [
          "text/plain",
          "application/json",
          "text/json"
        ],
        "StatusCode": 200
      }
    ]
  }
]